cmem_plugin_shapes/__init__.py
cmem_plugin_shapes/plugin_shapes.py
cmem_plugin_shapes/prefix_cc.json
cmem_plugin_shapes/shapes.svg
cmem_plugin_shapes-4.3.0.dist-info/METADATA
cmem_plugin_shapes-4.3.0.dist-info/WHEEL
cmem_plugin_shapes-4.3.0.dist-info/licenses/LICENSE
cmem_plugin_shapes-4.3.0.dist-info/RECORD
