Metadata-Version: 2.4
Name: cmem-plugin-shapes
Version: 4.3.0
Summary: Generate SHACL shapes from an instance data graph.
License: Apache-2.0
License-File: LICENSE
Keywords: eccenca Corporate Memory,plugin
Author: eccenca GmbH
Author-email: cmempy-developer@eccenca.com
Requires-Python: >=3.13,<4.0
Classifier: Development Status :: 4 - Beta
Classifier: Environment :: Plugins
Classifier: License :: OSI Approved :: Apache Software License
Classifier: Programming Language :: Python :: 3
Classifier: Programming Language :: Python :: 3.13
Classifier: Programming Language :: Python :: 3.14
Requires-Dist: cmem-cmempy (>=25,<26)
Requires-Dist: cmem-plugin-base (>=4.15.0,<5.0.0)
Requires-Dist: rdflib (>=7.1.4,<8.0.0)
Requires-Dist: validators (>=0.35.0,<0.36.0)
Project-URL: Homepage, https://github.com/eccenca/cmem-plugin-shapes
